penaltymodel/__init__.py
penaltymodel/mip/__init__.py
penaltymodel/mip/generation.py
penaltymodel/mip/interface.py
penaltymodel/mip/package_info.py
penaltymodel_mip-0.2.6.dist-info/METADATA
penaltymodel_mip-0.2.6.dist-info/WHEEL
penaltymodel_mip-0.2.6.dist-info/entry_points.txt
penaltymodel_mip-0.2.6.dist-info/top_level.txt
penaltymodel_mip-0.2.6.dist-info/RECORD
