Metadata-Version: 2.1
Name: penaltymodel-mip
Version: 0.2.6
Summary: Generates penalty models using Google Optimization Tools' Mixed-Integer Programming capability.
Home-page: https://github.com/dwavesystems/penaltymodel
Author: D-Wave Systems Inc.
Author-email: acondello@dwavesys.com
License: Apache 2.0
Platform: UNKNOWN
Classifier: License :: OSI Approved :: Apache Software License
Classifier: Operating System :: MacOS :: MacOS X
Classifier: Operating System :: Microsoft :: Windows
Classifier: Operating System :: POSIX :: Linux
Classifier: Programming Language :: Python :: 3
Classifier: Programming Language :: Python :: 3.6
Classifier: Programming Language :: Python :: 3.7
Classifier: Programming Language :: Python :: 3.8
Classifier: Programming Language :: Python :: 3.9
Classifier: Programming Language :: Python :: 3.10
Requires-Python: >=3.6
Requires-Dist: dimod (<0.11.0,>=0.8.0)
Requires-Dist: networkx (<3.0,>=2.4)
Requires-Dist: ortools (<10.0.0,>=6.6.4659)
Requires-Dist: penaltymodel (<0.17.0,>=0.16.0)
